{
  "name": "s1_tops_split",
  "description": "The method provides a convenient way to split each subswath with selected bursts into a separate product.",
  "label": "S1 TOPS Split",
  "parameters": {
    "selectedPolarisations": {
      "name": "selectedPolarisations",
      "options": [
        "VV",
        "HV"
      ],
      "index": 0,
      "defaultvalue": "VV",
      "label": "Polarisations",
      "type": "inputTypes.select",
      "value": "VV"
    },
    "firstBurstIndex": {
      "name": "firstBurstIndex",
      "index": 3,
      "defaultvalue": "-1",
      "label": "First Burst Index",
      "type": "inputTypes.text",
      "value": "7"
    },
    "lastBurstIndex": {
      "name": "lastBurstIndex",
      "index": 4,
      "defaultvalue": "-1",
      "label": "Last Burst Index",
      "type": "inputTypes.text",
      "value": "8"
    }
  }
}